gpt_gateway/__init__.py
gpt_gateway/client.py
gpt_gateway/collection.py
gpt_gateway/config.py
gpt_gateway/gptg_session.py
gpt_gateway/login.py
gpt_gateway/org.py
gpt_gateway/models/__init__.py
gpt_gateway/models/auth.py
gpt_gateway/models/chat.py
gpt_gateway/models/chatmodel.py
gpt_gateway/models/chunk.py
gpt_gateway/models/collection.py
gpt_gateway/models/embedding.py
gpt_gateway/models/metadata.py
gpt_gateway/models/models.py
gpt_gateway/models/org.py
gpt_gateway/models/plugin.py
gpt_gateway/models/prompt.py
gpt_gateway/models/providers.py
gpt_gateway/models/user.py
gpt_gateway-0.0.14.dist-info/LICENSE
gpt_gateway-0.0.14.dist-info/METADATA
gpt_gateway-0.0.14.dist-info/WHEEL
gpt_gateway-0.0.14.dist-info/top_level.txt
gpt_gateway-0.0.14.dist-info/RECORD
