Metadata-Version: 2.1
Name: gpt-gateway
Version: 0.0.14
Summary: Client for GPT-Gateway.com including ChatGPT Retreiver Plugins
Author-email: Bill Kish <bk@jiggy.ai>
Project-URL: Homepage, https://github.com/jiggy-ai/gpt-gateway-client
Project-URL: Bug Tracker, https://github.com/jiggy-ai/gpt-gateway-client/issues
Classifier: Programming Language :: Python :: 3
Classifier: License :: OSI Approved :: Apache Software License
Classifier: Operating System :: OS Independent
Requires-Python: >=3.9
License-File: LICENSE
Requires-Dist: loguru
Requires-Dist: pedantic[email]
Requires-Dist: requests
